dbt_unit_test/__init__.py
dbt_unit_test/app.py
dbt_unit_test/log_setup.py
dbt_unit_test/operations.py
dbt_unit_test-0.0.1.dist-info/LICENSE
dbt_unit_test-0.0.1.dist-info/METADATA
dbt_unit_test-0.0.1.dist-info/WHEEL
dbt_unit_test-0.0.1.dist-info/entry_points.txt
dbt_unit_test-0.0.1.dist-info/top_level.txt
dbt_unit_test-0.0.1.dist-info/RECORD
