Metadata-Version: 2.1
Name: dbt-unit-test
Version: 0.0.1
Summary: A tiny framework for testing reusable code inside of dbt models
Home-page: https://github.com/AgeOfLearning/dbt-unit-test
Author: Benjamin Ryon
Author-email: benjamin.ryon@aofl.com
License: UNKNOWN
Keywords: sql dbt test unittest
Platform: UNKNOWN
Classifier: Intended Audience :: Information Technology
Classifier: License :: OSI Approved :: MIT License
Classifier: Programming Language :: Python :: 3.8
Requires-Python: >=3.6
Requires-Dist: click
Requires-Dist: jinja2
Provides-Extra: dev
Requires-Dist: pytest ; extra == 'dev'
Requires-Dist: pytest-cov ; extra == 'dev'
Requires-Dist: pre-commit ; extra == 'dev'
Provides-Extra: test
Requires-Dist: pytest ; extra == 'test'
Requires-Dist: pytest-cov ; extra == 'test'
